tomlparams/__init__.py
tomlparams/console.py
tomlparams/examples/readme/__init__.py
tomlparams/examples/readme/base.toml
tomlparams/examples/readme/defaults.toml
tomlparams/examples/readme/defaults2.toml
tomlparams/examples/readme/hier.toml
tomlparams/examples/readme/newparam.toml
tomlparams/examples/readme/one.toml
tomlparams/examples/readme/readme1.py
tomlparams/examples/readme/readme2.py
tomlparams/examples/readme/readme3.py
tomlparams/examples/readme/readme4.py
tomlparams/examples/readme/three.toml
tomlparams/examples/readme/two.toml
tomlparams/params_group.py
tomlparams/parse_helpers.py
tomlparams/tests/__init__.py
tomlparams/tests/captureoutput.py
tomlparams/tests/test_parse_helpers.py
tomlparams/tests/test_tomlparams.py
tomlparams/tests/test_utils.py
tomlparams/tests/testdata/expected/deep.toml
tomlparams/tests/testdata/expected/one.toml
tomlparams/tests/testdata/expected/saveable.toml
tomlparams/tests/testdata/expected/self.toml
tomlparams/tests/testdata/expected/three.toml
tomlparams/tests/testdata/expected/two.toml
tomlparams/tests/testdata/expected/unchanged.toml
tomlparams/tests/testdata/expected/user_only.toml
tomlparams/tests/testdata/tomlparams/base.toml
tomlparams/tests/testdata/tomlparams/deep.toml
tomlparams/tests/testdata/tomlparams/defaults_as_dir/animals/birds.toml
tomlparams/tests/testdata/tomlparams/defaults_as_dir/animals/fish/salmon.toml
tomlparams/tests/testdata/tomlparams/defaults_as_dir/animals/fish/tuna.toml
tomlparams/tests/testdata/tomlparams/defaults_as_dir/fungi/ascomycota.toml
tomlparams/tests/testdata/tomlparams/defaults_as_dir/fungi/chytridiomycota.toml
tomlparams/tests/testdata/tomlparams/defaults_as_dir/human.toml
tomlparams/tests/testdata/tomlparams/defaults_as_dir_repeated_keys/human.toml
tomlparams/tests/testdata/tomlparams/defaults_as_dir_repeated_keys/stinky-human.toml
tomlparams/tests/testdata/tomlparams/defaults_as_file.toml
tomlparams/tests/testdata/tomlparams/five.toml
tomlparams/tests/testdata/tomlparams/four.toml
tomlparams-0.1.42.dist-info/AUTHORS
tomlparams-0.1.42.dist-info/LICENSE
tomlparams-0.1.42.dist-info/METADATA
tomlparams-0.1.42.dist-info/WHEEL
tomlparams-0.1.42.dist-info/entry_points.txt
tomlparams-0.1.42.dist-info/RECORD
