Metadata-Version: 2.3
Name: tomlparams
Version: 0.1.42
Summary: 
Author: Paola Arce @mapsa
Requires-Python: >=3.9,<4.0
Classifier: Programming Language :: Python :: 3
Classifier: Programming Language :: Python :: 3.9
Classifier: Programming Language :: Python :: 3.10
Classifier: Programming Language :: Python :: 3.11
Classifier: Programming Language :: Python :: 3.12
Classifier: Programming Language :: Python :: 3.13
Requires-Dist: tomli (>=2.0.1)
Requires-Dist: tomli-w (>=1.0.0)
